Metadata-Version: 2.1
Name: keras-octave-conv
Version: 0.11.0
Summary: Octave convolution
Home-page: https://github.com/CyberZHG/keras-octave-conv
Author: CyberZHG
Author-email: CyberZHG@users.noreply.github.com
License: MIT AND "Anti 996"
Platform: UNKNOWN
Classifier: Programming Language :: Python :: 3
Classifier: License :: OSI Approved :: MIT License
Classifier: Operating System :: OS Independent
